spell_check_client/__init__.py
spell_check_client/_configuration.py
spell_check_client/_spell_check_client.py
spell_check_client/version.py
spell_check_client/aio/__init__.py
spell_check_client/aio/_configuration.py
spell_check_client/aio/_spell_check_client.py
spell_check_client/aio/operations/__init__.py
spell_check_client/aio/operations/_spell_check_client_operations.py
spell_check_client/models/__init__.py
spell_check_client/models/_models.py
spell_check_client/models/_models_py3.py
spell_check_client/models/_spell_check_client_enums.py
spell_check_client/operations/__init__.py
spell_check_client/operations/_spell_check_client_operations.py
microsoft_bing_spellcheck-1.0.0.dist-info/LICENSE.txt
microsoft_bing_spellcheck-1.0.0.dist-info/METADATA
microsoft_bing_spellcheck-1.0.0.dist-info/WHEEL
microsoft_bing_spellcheck-1.0.0.dist-info/top_level.txt
microsoft_bing_spellcheck-1.0.0.dist-info/RECORD
